FullSpeedPythonZhongwenban/README.md
FullSpeedPythonZhongwenban/__init__.py
FullSpeedPythonZhongwenban/__main__.py
FullSpeedPythonZhongwenban/file.epub
FullSpeedPythonZhongwenban/index.html
FullSpeedPythonZhongwenban/css/__init__.py
FullSpeedPythonZhongwenban/css/annotations.css
FullSpeedPythonZhongwenban/css/main.css
FullSpeedPythonZhongwenban/css/normalize.css
FullSpeedPythonZhongwenban/css/popup.css
FullSpeedPythonZhongwenban/font/__init__.py
FullSpeedPythonZhongwenban/font/fontello.eot
FullSpeedPythonZhongwenban/font/fontello.svg
FullSpeedPythonZhongwenban/font/fontello.ttf
FullSpeedPythonZhongwenban/font/fontello.woff
FullSpeedPythonZhongwenban/img/__init__.py
FullSpeedPythonZhongwenban/img/annotator-glyph-sprite.png
FullSpeedPythonZhongwenban/img/annotator-icon-sprite.png
FullSpeedPythonZhongwenban/img/apple-touch-icon.png
FullSpeedPythonZhongwenban/img/cancelfullscreen.png
FullSpeedPythonZhongwenban/img/close.png
FullSpeedPythonZhongwenban/img/fullscreen.png
FullSpeedPythonZhongwenban/img/loader.gif
FullSpeedPythonZhongwenban/img/menu-icon.png
FullSpeedPythonZhongwenban/img/save.png
FullSpeedPythonZhongwenban/img/saved.png
FullSpeedPythonZhongwenban/img/settings-s.png
FullSpeedPythonZhongwenban/img/settings.png
FullSpeedPythonZhongwenban/img/star.png
FullSpeedPythonZhongwenban/js/__init__.py
FullSpeedPythonZhongwenban/js/epub.js
FullSpeedPythonZhongwenban/js/epub.min.js
FullSpeedPythonZhongwenban/js/epub.min.map
FullSpeedPythonZhongwenban/js/hooks.min.js
FullSpeedPythonZhongwenban/js/hooks.min.map
FullSpeedPythonZhongwenban/js/reader.js
FullSpeedPythonZhongwenban/js/reader.js.map
FullSpeedPythonZhongwenban/js/reader.min.js
FullSpeedPythonZhongwenban/js/reader.min.map
FullSpeedPythonZhongwenban/js/hooks/__init__.py
FullSpeedPythonZhongwenban/js/hooks/extensions/__init__.py
FullSpeedPythonZhongwenban/js/hooks/extensions/highlight.js
FullSpeedPythonZhongwenban/js/libs/__init__.py
FullSpeedPythonZhongwenban/js/libs/jquery.min.js
full_speed_python_zhongwenban-2024.3.5.0.dist-info/METADATA
full_speed_python_zhongwenban-2024.3.5.0.dist-info/WHEEL
full_speed_python_zhongwenban-2024.3.5.0.dist-info/entry_points.txt
full_speed_python_zhongwenban-2024.3.5.0.dist-info/top_level.txt
full_speed_python_zhongwenban-2024.3.5.0.dist-info/RECORD
